{
  "row_count": 11630,
  "prompt_pair_count": 5815,
  "valid_pair_count": 5815,
  "label_counts": {
    "NORMAL": 5815,
    "LOW_DIVERSITY": 1078,
    "HIGH_DIVERSITY": 4737
  },
  "hallucinated_label_pair_counts": {
    "LOW_DIVERSITY": 1078,
    "HIGH_DIVERSITY": 4737
  },
  "semantic_entropy_shared_pair_count": 5815,
  "semantic_entropy_shared_pair_fraction": 1.0,
  "high_diversity_prompt_count": 4737,
  "low_diversity_prompt_count": 1078,
  "low_diversity_results": [
    {
      "signal": "semantic_energy_boltzmann",
      "subset": "LOW_DIVERSITY",
      "orientation": "higher candidate Boltzmann-style diagnostic means higher risk",
      "pair_count": 1078,
      "win_rate_hallucinated_risk_gt_normal": 0.5797773654916512,
      "tie_rate": 0.0018552875695732839,
      "mean_delta_hallucinated_minus_normal": 0.18972103448484565,
      "median_delta_hallucinated_minus_normal": 0.38090418353576183,
      "bootstrap_win_rate_ci95": [
        0.5500927643784786,
        0.6094619666048238
      ],
      "candidate_row_auroc_within_subset": 0.5529071048220267,
      "candidate_row_auprc_within_subset": 0.5108179521904034,
      "by_dataset": {
        "HaluEval-QA": {
          "pair_count": 1066,
          "win_rate": 0.5769230769230769,
          "tie_rate": 0.001876172607879925,
          "mean_delta": 0.18234852463560783,
          "median_delta": 0.366826923076923
        },
        "TruthfulQA": {
          "pair_count": 12,
          "win_rate": 0.8333333333333334,
          "tie_rate": 0.0,
          "mean_delta": 0.8446456594254702,
          "median_delta": 0.5135060817805375
        }
      }
    },
    {
      "signal": "logit_variance",
      "subset": "LOW_DIVERSITY",
      "orientation": "higher logit variance means higher risk",
      "pair_count": 1078,
      "win_rate_hallucinated_risk_gt_normal": 0.7077922077922078,
      "tie_rate": 0.0,
      "mean_delta_hallucinated_minus_normal": 0.4535441118904136,
      "median_delta_hallucinated_minus_normal": 0.5309046027148958,
      "bootstrap_win_rate_ci95": [
        0.6799628942486086,
        0.7346938775510204
      ],
      "candidate_row_auroc_within_subset": 0.6786592019165567,
      "candidate_row_auprc_within_subset": 0.5867185666300874,
      "by_dataset": {
        "HaluEval-QA": {
          "pair_count": 1066,
          "win_rate": 0.7110694183864915,
          "tie_rate": 0.0,
          "mean_delta": 0.46396624997091274,
          "median_delta": 0.5372349170731572
        },
        "TruthfulQA": {
          "pair_count": 12,
          "win_rate": 0.4166666666666667,
          "tie_rate": 0.0,
          "mean_delta": -0.47228915426059775,
          "median_delta": -0.5567490848950856
        }
      }
    },
    {
      "signal": "negative_confidence_margin",
      "subset": "LOW_DIVERSITY",
      "orientation": "lower confidence margin means higher confident-wrong risk",
      "pair_count": 1078,
      "win_rate_hallucinated_risk_gt_normal": 0.8051948051948052,
      "tie_rate": 0.0009276437847866419,
      "mean_delta_hallucinated_minus_normal": 1.3686204260401278,
      "median_delta_hallucinated_minus_normal": 1.5200396825396825,
      "bootstrap_win_rate_ci95": [
        0.7810760667903525,
        0.8283858998144712
      ],
      "candidate_row_auroc_within_subset": 0.7704486078459043,
      "candidate_row_auprc_within_subset": 0.6901761629262253,
      "by_dataset": {
        "HaluEval-QA": {
          "pair_count": 1066,
          "win_rate": 0.8067542213883677,
          "tie_rate": 0.0009380863039399625,
          "mean_delta": 1.380307977785957,
          "median_delta": 1.5275327620967742
        },
        "TruthfulQA": {
          "pair_count": 12,
          "win_rate": 0.6666666666666666,
          "tie_rate": 0.0,
          "mean_delta": 0.3303762459522929,
          "median_delta": 0.43763130252100835
        }
      }
    },
    {
      "signal": "negative_mean_negative_log_probability",
      "subset": "LOW_DIVERSITY",
      "orientation": "lower mean NLL means higher confident-wrong risk",
      "pair_count": 1078,
      "win_rate_hallucinated_risk_gt_normal": 0.5871985157699443,
      "tie_rate": 0.0,
      "mean_delta_hallucinated_minus_normal": 0.9199862690934689,
      "median_delta_hallucinated_minus_normal": 0.2866753472222223,
      "bootstrap_win_rate_ci95": [
        0.5584415584415584,
        0.6159554730983302
      ],
      "candidate_row_auroc_within_subset": 0.6024461226555051,
      "candidate_row_auprc_within_subset": 0.587262986819214,
      "by_dataset": {
        "HaluEval-QA": {
          "pair_count": 1066,
          "win_rate": 0.5909943714821764,
          "tie_rate": 0.0,
          "mean_delta": 0.9408832428920396,
          "median_delta": 0.2984165969899666
        },
        "TruthfulQA": {
          "pair_count": 12,
          "win_rate": 0.25,
          "tie_rate": 0.0,
          "mean_delta": -0.9363615700128897,
          "median_delta": -0.6608072916666667
        }
      }
    },
    {
      "signal": "corpus_risk_only",
      "subset": "LOW_DIVERSITY",
      "orientation": "higher corpus risk means higher risk",
      "pair_count": 1078,
      "win_rate_hallucinated_risk_gt_normal": 0.49165120593692024,
      "tie_rate": 0.01948051948051948,
      "mean_delta_hallucinated_minus_normal": -0.0006699647495361792,
      "median_delta_hallucinated_minus_normal": 0.0,
      "bootstrap_win_rate_ci95": [
        0.461038961038961,
        0.5204081632653061
      ],
      "candidate_row_auroc_within_subset": 0.48745959844555126,
      "candidate_row_auprc_within_subset": 0.4467291964653224,
      "by_dataset": {
        "HaluEval-QA": {
          "pair_count": 1066,
          "win_rate": 0.4915572232645403,
          "tie_rate": 0.019699812382739212,
          "mean_delta": -0.0008216810506566601,
          "median_delta": 0.0
        },
        "TruthfulQA": {
          "pair_count": 12,
          "win_rate": 0.5,
          "tie_rate": 0.0,
          "mean_delta": 0.01280749999999999,
          "median_delta": -0.00031500000000006523
        }
      }
    }
  ],
  "all_pair_results": [
    {
      "signal": "semantic_energy_boltzmann",
      "subset": "ALL_VALID_PAIRS",
      "orientation": "higher candidate Boltzmann-style diagnostic means higher risk",
      "pair_count": 5815,
      "win_rate_hallucinated_risk_gt_normal": 0.5105760963026655,
      "tie_rate": 0.0060189165950128975,
      "mean_delta_hallucinated_minus_normal": -0.07052786438943051,
      "median_delta_hallucinated_minus_normal": 0.03935185185185475,
      "bootstrap_win_rate_ci95": [
        0.49767841788478073,
        0.5234737747205503
      ],
      "candidate_row_auroc_within_subset": 0.4947682816920986,
      "candidate_row_auprc_within_subset": 0.4646562848277306,
      "by_dataset": {
        "HaluEval-QA": {
          "pair_count": 5000,
          "win_rate": 0.505,
          "tie_rate": 0.0036,
          "mean_delta": -0.11284543229991213,
          "median_delta": 0.02083333333333215
        },
        "TruthfulQA": {
          "pair_count": 815,
          "win_rate": 0.5447852760736196,
          "tie_rate": 0.020858895705521473,
          "mean_delta": 0.189089116656469,
          "median_delta": 0.1284340659340657
        }
      }
    },
    {
      "signal": "logit_variance",
      "subset": "ALL_VALID_PAIRS",
      "orientation": "higher logit variance means higher risk",
      "pair_count": 5815,
      "win_rate_hallucinated_risk_gt_normal": 0.6285468615649183,
      "tie_rate": 0.004815133276010318,
      "mean_delta_hallucinated_minus_normal": 0.2958541994427812,
      "median_delta_hallucinated_minus_normal": 0.3168413246286228,
      "bootstrap_win_rate_ci95": [
        0.6159888220120379,
        0.6411006018916595
      ],
      "candidate_row_auroc_within_subset": 0.6044153902684447,
      "candidate_row_auprc_within_subset": 0.5290097792243604,
      "by_dataset": {
        "HaluEval-QA": {
          "pair_count": 5000,
          "win_rate": 0.667,
          "tie_rate": 0.0022,
          "mean_delta": 0.376382816633815,
          "median_delta": 0.43237981786941626
        },
        "TruthfulQA": {
          "pair_count": 815,
          "win_rate": 0.39263803680981596,
          "tie_rate": 0.020858895705521473,
          "mean_delta": -0.19818639682123082,
          "median_delta": -0.1414197577107803
        }
      }
    },
    {
      "signal": "negative_confidence_margin",
      "subset": "ALL_VALID_PAIRS",
      "orientation": "lower confidence margin means higher confident-wrong risk",
      "pair_count": 5815,
      "win_rate_hallucinated_risk_gt_normal": 0.6471195184866724,
      "tie_rate": 0.0060189165950128975,
      "mean_delta_hallucinated_minus_normal": 0.6271289330331162,
      "median_delta_hallucinated_minus_normal": 0.7333333333333334,
      "bootstrap_win_rate_ci95": [
        0.634737747205503,
        0.65932932072227
      ],
      "candidate_row_auroc_within_subset": 0.6191945401676365,
      "candidate_row_auprc_within_subset": 0.5295868673678426,
      "by_dataset": {
        "HaluEval-QA": {
          "pair_count": 5000,
          "win_rate": 0.6822,
          "tie_rate": 0.0034,
          "mean_delta": 0.7635001788771713,
          "median_delta": 0.9787660256410258
        },
        "TruthfulQA": {
          "pair_count": 815,
          "win_rate": 0.43190184049079755,
          "tie_rate": 0.022085889570552148,
          "mean_delta": -0.20950447705311098,
          "median_delta": -0.11562499999999998
        }
      }
    },
    {
      "signal": "negative_mean_negative_log_probability",
      "subset": "ALL_VALID_PAIRS",
      "orientation": "lower mean NLL means higher confident-wrong risk",
      "pair_count": 5815,
      "win_rate_hallucinated_risk_gt_normal": 0.6142734307824591,
      "tie_rate": 0.00034393809114359415,
      "mean_delta_hallucinated_minus_normal": 1.160251470185592,
      "median_delta_hallucinated_minus_normal": 0.47115384615384626,
      "bootstrap_win_rate_ci95": [
        0.6018916595012898,
        0.6266552020636286
      ],
      "candidate_row_auroc_within_subset": 0.6270087071343495,
      "candidate_row_auprc_within_subset": 0.5790279330124141,
      "by_dataset": {
        "HaluEval-QA": {
          "pair_count": 5000,
          "win_rate": 0.6208,
          "tie_rate": 0.0002,
          "mean_delta": 1.2957024282743708,
          "median_delta": 0.53125
        },
        "TruthfulQA": {
          "pair_count": 815,
          "win_rate": 0.5742331288343558,
          "tie_rate": 0.001226993865030675,
          "mean_delta": 0.32926399724829725,
          "median_delta": 0.1875
        }
      }
    },
    {
      "signal": "corpus_risk_only",
      "subset": "ALL_VALID_PAIRS",
      "orientation": "higher corpus risk means higher risk",
      "pair_count": 5815,
      "win_rate_hallucinated_risk_gt_normal": 0.5057609630266552,
      "tie_rate": 0.028546861564918313,
      "mean_delta_hallucinated_minus_normal": 0.008749246775580394,
      "median_delta_hallucinated_minus_normal": 0.0023769999999999625,
      "bootstrap_win_rate_ci95": [
        0.49286328460877044,
        0.51865864144454
      ],
      "candidate_row_auroc_within_subset": 0.5176744846288802,
      "candidate_row_auprc_within_subset": 0.4687560538470297,
      "by_dataset": {
        "HaluEval-QA": {
          "pair_count": 5000,
          "win_rate": 0.5254,
          "tie_rate": 0.0234,
          "mean_delta": 0.013484966799999998,
          "median_delta": 0.010390999999999984
        },
        "TruthfulQA": {
          "pair_count": 815,
          "win_rate": 0.3852760736196319,
          "tie_rate": 0.06012269938650307,
          "mean_delta": -0.020304250306748466,
          "median_delta": -0.014373000000000025
        }
      }
    }
  ],
  "conclusion_notes": [
    "Semantic Entropy is shared within every valid prompt pair, confirming candidate-row AUROC is not an appropriate within-pair SE test.",
    "LOW_DIVERSITY paired win rates are the relevant first-pass test for Energy/logit complementarity.",
    "Dataset breakdown is required because LOW_DIVERSITY pairs are dominated by HaluEval-QA.",
    "Corpus risk is reported here as diagnostic; current learned fusion with corpus should not be claimed as aggregate improvement."
  ]
}
